Metadata-Version: 2.1
Name: shellypy2
Version: 0.4.0.3
Summary: Wrapper around the Shelly HTTP api forked from shellypy
Home-page: https://github.com/SeRoWo83/ShellyPy
Author: Sebastian Wolf
Author-email: sebastian.wolf@pace-systems.de
License: MIT
Classifier: Programming Language :: Python :: 3
Classifier: License :: OSI Approved :: MIT License
Classifier: Operating System :: OS Independent
Requires-Python: >=3.10
License-File: LICENSE
Requires-Dist: requests
Requires-Dist: types-requests
Requires-Dist: numpy
